daikin.py
src/daikin_cloud_crossan007/daikin_api.py
src/daikin_cloud_crossan007/daikin_cloud.py
src/daikin_cloud_crossan007/daikin_device.py
src/daikin_cloud_crossan007/daikin_device_data.py
src/daikin_cloud_crossan007/daikin_installation.py
src/daikin_cloud_crossan007/daikin_profile.py
src/daikin_cloud_crossan007/logger.py
daikin_cloud_crossan007-0.1.0.dist-info/METADATA
daikin_cloud_crossan007-0.1.0.dist-info/WHEEL
daikin_cloud_crossan007-0.1.0.dist-info/licenses/LICENSE
daikin_cloud_crossan007-0.1.0.dist-info/RECORD
