Metadata-Version: 2.1
Name: daikin_cloud_crossan007
Version: 0.1.0
Summary: A set of Python classes to interact with and control Daikin HVAC units associated with a DKNOne / Daikin Cloud NA account
Project-URL: Homepage, https://github.com/crossan007/python-daikin_cloud
Project-URL: Bug Tracker, https://github.com/crossan007/python-daikin_cloud/issues
Author-email: Charles Crossan <crossan007@gmail.com>
License-File: LICENSE
Classifier: License :: OSI Approved :: MIT License
Classifier: Operating System :: OS Independent
Classifier: Programming Language :: Python :: 3
Requires-Python: >=3.7
